{
    "uuids": {
        "phone_id": "ecbf5552-3b41-44dc-9063-11cf4da01de1",
        "uuid": "8d2f7086-63c2-4c31-918f-0bbcb979e267",
        "client_session_id": "c201d7e4-3c58-4008-b168-5713e54fc99f",
        "advertising_id": "fe920fa4-5b7e-49da-a824-71f718c5ba4b",
        "android_device_id": "android-32ed695231e08495",
        "request_id": "01dc53d5-89de-47f2-a904-24813a56f210",
        "tray_session_id": "78db296f-396f-4d4b-a966-da4aab314cf4"
    },
    "mid": "Z7zjigABAAHpxPJYYEILRzWnMYQL",
    "ig_u_rur": null,
    "ig_www_claim": null,
    "authorization_data": {
        "ds_user_id": "72562215441",
        "sessionid": "72562215441%3AJqkSmgbKEPKKx8%3A28%3AAYdpVBFBKnmD15QdW8EtzPedrFAZ4dw-Dtc2UzTy1Q"
    },
    "cookies": {},
    "last_login": 1740432327.2908733,
    "device_settings": {
        "app_version": "269.0.0.18.75",
        "android_version": 26,
        "android_release": "8.0.0",
        "dpi": "480dpi",
        "resolution": "1080x1920",
        "manufacturer": "OnePlus",
        "device": "devitron",
        "model": "6T Dev",
        "cpu": "qcom",
        "version_code": "314665256"
    },
    "user_agent": "Instagram 269.0.0.18.75 Android (26/8.0.0; 480dpi; 1080x1920; OnePlus; 6T Dev; devitron; qcom; en_US; 314665256)",
    "country": "US",
    "country_code": 1,
    "locale": "en_US",
    "timezone_offset": -14400
}